Metadata-Version: 1.0
Name: pyscf-doci
Version: 0.1.0
Summary: doubly-occupied configuration interaction
Home-page: UNKNOWN
Author: Qiming Sun
Author-email: osirpt.sun@gmail.com
License: UNKNOWN
Platform: UNKNOWN
